haystack_integrations/components/retrievers/py.typed
haystack_integrations/components/retrievers/azure_ai_search/__init__.py
haystack_integrations/components/retrievers/azure_ai_search/bm25_retriever.py
haystack_integrations/components/retrievers/azure_ai_search/embedding_retriever.py
haystack_integrations/components/retrievers/azure_ai_search/hybrid_retriever.py
haystack_integrations/document_stores/py.typed
haystack_integrations/document_stores/azure_ai_search/__init__.py
haystack_integrations/document_stores/azure_ai_search/document_store.py
haystack_integrations/document_stores/azure_ai_search/errors.py
haystack_integrations/document_stores/azure_ai_search/filters.py
azure_ai_search_haystack-3.0.0.dist-info/METADATA
azure_ai_search_haystack-3.0.0.dist-info/WHEEL
azure_ai_search_haystack-3.0.0.dist-info/licenses/LICENSE
azure_ai_search_haystack-3.0.0.dist-info/RECORD
