Metadata-Version: 2.4
Name: azure-ai-search-haystack
Version: 3.0.0
Summary: Haystack 2.x Document Store for Azure AI Search
Project-URL: Documentation, https://github.com/deepset-ai/haystack-core-integrations/tree/main/integrations/azure_ai_search#readme
Project-URL: Issues, https://github.com/deepset-ai/haystack-core-integrations/issues
Project-URL: Source, https://github.com/deepset-ai/haystack-core-integrations/tree/main/integrations/azure_ai_search
Author-email: deepset <info@deepset.ai>
License-Expression: Apache-2.0
License-File: LICENSE
Classifier: Development Status :: 4 - Beta
Classifier: License :: OSI Approved :: Apache Software License
Classifier: Programming Language :: Python
Classifier: Programming Language :: Python :: 3.10
Classifier: Programming Language :: Python :: 3.11
Classifier: Programming Language :: Python :: 3.12
Classifier: Programming Language :: Python :: 3.13
Classifier: Programming Language :: Python :: Implementation :: CPython
Classifier: Programming Language :: Python :: Implementation :: PyPy
Requires-Python: >=3.10
Requires-Dist: azure-identity
Requires-Dist: azure-search-documents>=11.5
Requires-Dist: haystack-ai>=2.22.0
